{
  "Name": "azure-storage-blobs",
  "Version": "12.17.0-beta.1",
  "DevVersion": null,
  "DirectoryPath": "sdk/storage/azure-storage-blobs",
  "ServiceDirectory": "storage",
  "ReadMePath": "sdk/storage/azure-storage-blobs/README.md",
  "ChangeLogPath": "sdk/storage/azure-storage-blobs/CHANGELOG.md",
  "Group": null,
  "SdkType": "client",
  "IsNewSdk": true,
  "ArtifactName": "azure-storage-blobs",
  "ReleaseStatus": "2026-02-26",
  "IncludedForValidation": false,
  "AdditionalValidationPackages": null,
  "ArtifactDetails": {
    "Name": "azure-storage-blobs",
    "Path": "azure-storage-blobs",
    "VcpkgPortName": "azure-storage-blobs-cpp",
    "triggeringPaths": [
      "/sdk/storage/ci.yml"
    ]
  },
  "CIParameters": {
    "CIMatrixConfigs": []
  },
  "SpecProjectPath": null
}
